tools_commons/__init__.py
tools_commons/cache_loaders.py
tools_commons/collections.py
tools_commons/decorator.py
tools_commons/exceptions.py
tools_commons/functions.py
tools_commons/http_utils.py
tools_commons/misc_utils.py
tools_commons/ms_teams_alerter.py
tools_commons/pager_duty_alerter.py
tools_commons/regex_utils.py
tools_commons/registry.py
tools_commons/singleton.py
tools_commons/slack_alerter.py
tools_commons/teams_alert_template.py
tools_commons/logging/__init__.py
tools_commons/logging/atlas_counter.py
tools_commons/logging/logs.py
tools_commons/logging/async_logger/__init__.py
tools_commons/logging/async_logger/log_loop.py
tools_commons/logging/async_logger/handlers/__init__.py
tools_commons/logging/async_logger/handlers/file_log_handler.py
tools_commons/logging/async_logger/handlers/slack_log_handler.py
tools_commons/logging/async_logger/handlers/stream_log_handler.py
tools_commons/pubsub/__init__.py
tools_commons/pubsub/pub_sub_hub.py
tools_commons/pubsub/subscriber_registry.py
tools_commons/pubsub/topic_registry.py
tools_commons/scripts/__init__.py
tools_commons/scripts/jenkins.py
tools_commons/scripts/jenkins_async.py
tools_commons/scripts/uploader.py
tools_commons/serde_protocols/__init__.py
tools_commons/serde_protocols/my_pickle.py
tools_commons/serde_protocols/protocol.py
tools_commons/tests/__init__.py
tools_commons/tests/json_constants.py
tools_commons/tests/test_async_logger.py
tools_commons/tests/test_cache_loaders.py
tools_commons/tests/test_collections.py
tools_commons/tests/test_decorator.py
tools_commons/tests/test_exceptions.py
tools_commons/tests/test_registry.py
tools_commons/tests/test_run_coroutine.py
tools_commons-0.0.2.dist-info/METADATA
tools_commons-0.0.2.dist-info/WHEEL
tools_commons-0.0.2.dist-info/top_level.txt
tools_commons-0.0.2.dist-info/RECORD
