Metadata-Version: 2.1
Name: tools-commons
Version: 0.0.2
Summary: tools_commons component of pipelib
Home-page: https://github.com/teesign/pipelib
Author: 
Author-email: 
Classifier: Programming Language :: Python :: 3
Classifier: Operating System :: OS Independent
Requires-Python: >=3.6
Requires-Dist: aiobotocore ==2.1.1
Requires-Dist: aiologger ==0.6.1
Requires-Dist: boto3 ==1.20.24
Requires-Dist: cachetools ==4.0
Requires-Dist: python-jenkins ==1.5.0
Requires-Dist: Pillow
Requires-Dist: overrides ==1.9
Requires-Dist: requests
Requires-Dist: slack-sdk ==3.15.1
Requires-Dist: wget ==3.2
Requires-Dist: unidecode ==1.3.7
Requires-Dist: urllib3 <1.27,>=1.26.17
Requires-Dist: aiohttp ==3.9.4
Requires-Dist: aiofiles ==0.8.0
Requires-Dist: schedule
Requires-Dist: pymsteams ==0.2.2
Requires-Dist: httpx ==0.23.0
